doc/source/conf.py
doc/source/_themes/alabaster/__init__.py
doc/source/_themes/alabaster/_version.py
doc/source/_themes/alabaster/support.py
neomodel/__init__.py
neomodel/_version.py
neomodel/config.py
neomodel/constants.py
neomodel/exceptions.py
neomodel/hooks.py
neomodel/match_q.py
neomodel/properties.py
neomodel/py.typed
neomodel/semantic_filters.py
neomodel/typing.py
neomodel/util.py
neomodel/_async_compat/util.py
neomodel/async_/__init__.py
neomodel/async_/cardinality.py
neomodel/async_/database.py
neomodel/async_/match.py
neomodel/async_/node.py
neomodel/async_/path.py
neomodel/async_/property_manager.py
neomodel/async_/relationship.py
neomodel/async_/relationship_manager.py
neomodel/async_/transaction.py
neomodel/contrib/__init__.py
neomodel/contrib/spatial_properties.py
neomodel/contrib/async_/semi_structured.py
neomodel/contrib/sync_/semi_structured.py
neomodel/integration/numpy.py
neomodel/integration/pandas.py
neomodel/scripts/__init__.py
neomodel/scripts/neomodel_generate_diagram.py
neomodel/scripts/neomodel_inspect_database.py
neomodel/scripts/neomodel_install_labels.py
neomodel/scripts/neomodel_remove_labels.py
neomodel/scripts/utils.py
neomodel/sync_/__init__.py
neomodel/sync_/cardinality.py
neomodel/sync_/database.py
neomodel/sync_/match.py
neomodel/sync_/node.py
neomodel/sync_/path.py
neomodel/sync_/property_manager.py
neomodel/sync_/relationship.py
neomodel/sync_/relationship_manager.py
neomodel/sync_/transaction.py
neomodel-6.0.1.dist-info/licenses/AUTHORS.txt
neomodel-6.0.1.dist-info/licenses/LICENSE
test/__init__.py
test/conftest.py
test/diagram_classes.py
test/test_config_modernization.py
test/test_exceptions_additional.py
test/test_properties_additional.py
test/test_scripts.py
test/test_util.py
test/_async_compat/__init__.py
test/_async_compat/mark_decorator.py
test/async_/__init__.py
test/async_/conftest.py
test/async_/test_alias.py
test/async_/test_batch.py
test/async_/test_cardinality.py
test/async_/test_connection.py
test/async_/test_core_additional.py
test/async_/test_cypher.py
test/async_/test_database_management.py
neomodel-6.0.1.dist-info/METADATA
neomodel-6.0.1.dist-info/WHEEL
neomodel-6.0.1.dist-info/entry_points.txt
neomodel-6.0.1.dist-info/top_level.txt
neomodel-6.0.1.dist-info/RECORD
