Metadata-Version: 2.4
Name: neomodel
Version: 6.0.1
Summary: An object mapper for the neo4j graph database.
Author-email: Robin Edwards <robin.ge@gmail.com>
Maintainer-email: Marius Conjeaud <marius.conjeaud@outlook.com>, Antoine Nguyen <tonio@ngyn.org>, Athanasios Anastasiou <athanastasiou@gmail.com>
License: MIT
Project-URL: documentation, https://neomodel.readthedocs.io/en/latest/
Project-URL: repository, http://github.com/neo4j-contrib/neomodel
Project-URL: changelog, https://github.com/neo4j-contrib/neomodel/releases
Keywords: graph,neo4j,ORM,OGM,mapper
Classifier: Development Status :: 5 - Production/Stable
Classifier: Intended Audience :: Developers
Classifier: Operating System :: OS Independent
Classifier: License :: OSI Approved :: MIT License
Classifier: Programming Language :: Python
Classifier: Topic :: Software Development :: Libraries :: Python Modules
Classifier: Programming Language :: Python :: 3
Classifier: Topic :: Database
Requires-Python: >=3.10
License-File: LICENSE
License-File: AUTHORS.txt
Requires-Dist: neo4j~=6.0.3
Provides-Extra: extras
Requires-Dist: shapely; extra == "extras"
Requires-Dist: pandas; extra == "extras"
Requires-Dist: numpy; extra == "extras"
Provides-Extra: dev
Requires-Dist: unasync; extra == "dev"
Requires-Dist: pytest>=7.1; extra == "dev"
Requires-Dist: pytest-asyncio; extra == "dev"
Requires-Dist: pytest-cov>=4.0; extra == "dev"
Requires-Dist: pytest-mock; extra == "dev"
Requires-Dist: pre-commit; extra == "dev"
Requires-Dist: black; extra == "dev"
Requires-Dist: isort; extra == "dev"
Requires-Dist: mypy; extra == "dev"
Requires-Dist: pandas-stubs; extra == "dev"
Requires-Dist: types-shapely; extra == "dev"
Provides-Extra: shapely
Requires-Dist: Shapely>=2.0.0; extra == "shapely"
Provides-Extra: pandas
Requires-Dist: pandas; extra == "pandas"
Provides-Extra: numpy
Requires-Dist: numpy; extra == "numpy"
Provides-Extra: rust-driver-ext
Requires-Dist: neo4j-rust-ext~=6.0.3.0; extra == "rust-driver-ext"
Dynamic: license-file
